sentry_dingding/__init__.py
sentry_dingding/forms.py
sentry_dingding/plugin.py
sentry_dingding_sean-0.0.2.dist-info/DESCRIPTION.rst
sentry_dingding_sean-0.0.2.dist-info/METADATA
sentry_dingding_sean-0.0.2.dist-info/RECORD
sentry_dingding_sean-0.0.2.dist-info/WHEEL
sentry_dingding_sean-0.0.2.dist-info/entry_points.txt
sentry_dingding_sean-0.0.2.dist-info/metadata.json
sentry_dingding_sean-0.0.2.dist-info/top_level.txt
