Metadata-Version: 2.0
Name: sentry-dingding-sean
Version: 0.0.2
Summary: sean A Sentry extension which send errors stats to DingDing
Home-page: UNKNOWN
Author: sean
Author-email: ichenxiang@vip.qq.com
License: MIT
Keywords: sentry dingding
Platform: UNKNOWN
Classifier: Programming Language :: Python :: 2.7
Classifier: License :: OSI Approved :: MIT License
Requires-Dist: requests
Requires-Dist: sentry (>=9.0.0)
